LICENSE.txt
MANIFEST.in
README.rst
setup.py
pyutopia_tools.egg-info/PKG-INFO
pyutopia_tools.egg-info/SOURCES.txt
pyutopia_tools.egg-info/dependency_links.txt
pyutopia_tools.egg-info/not-zip-safe
pyutopia_tools.egg-info/requires.txt
pyutopia_tools.egg-info/top_level.txt
utopia/tools/__init__.py
utopia/tools/arxiv.py
utopia/tools/cited.py
utopia/tools/crossref.py
utopia/tools/doi.py
utopia/tools/eutils.py
utopia/tools/nlm.py
utopia/tools/pmc.py
utopia/tools/provenance.py
utopia/tools/pubmed.py
utopia/tools/title.py