Metadata-Version: 1.1
Name: pyutopia-tools
Version: 3.1.0.10
Summary: Utopia tools package
Home-page: https://github.com/lostislandlabs/python-utopia-tools
Author: David Thorne
Author-email: davethorne@gmail.com
License:                     GNU GENERAL PUBLIC LICENSE
